yxquantgene/__init__.py
yxquantgene/versions.py
yxquantgene/analyses/__init__.py
yxquantgene/analyses/clustering.py
yxquantgene/analyses/gwas.py
yxquantgene/analyses/pca.py
yxquantgene/analyses/psa.py
yxquantgene/metrics/__init__.py
yxquantgene/metrics/ibs.py
yxquantgene/metrics/ld.py
yxquantgene/metrics/pi.py
yxquantgene/metrics/tajimaD.py
yxquantgene/plot/__init__.py
yxquantgene/plot/geogenoplot.py
yxquantgene/plot/manhattan.py
yxquantgene/plot/qqplot.py
yxquantgene/utils/__init__.py
yxquantgene/utils/utils.py
yxquantgene/utils/vcf.py
yxquantgene-0.0.4.dist-info/LICENSE
yxquantgene-0.0.4.dist-info/METADATA
yxquantgene-0.0.4.dist-info/WHEEL
yxquantgene-0.0.4.dist-info/top_level.txt
yxquantgene-0.0.4.dist-info/RECORD
