Metadata-Version: 2.1
Name: yxquantgene
Version: 0.0.4
Summary: Xu Yuxing's personal quantitative genomic tools
Home-page: https://github.com/SouthernCD/yxquantgene
Author: Yuxing Xu
Author-email: xuyuxing@mail.kib.ac.cn
Requires-Python: >=3.5
License-File: LICENSE
Requires-Dist: scikit-learn
Requires-Dist: pandas
Requires-Dist: yxutil
Requires-Dist: yxseq
Requires-Dist: statsmodels
Requires-Dist: matplotlib
Requires-Dist: pysam
Requires-Dist: yxmath
Requires-Dist: numpy
Requires-Dist: joblib
Requires-Dist: seaborn
Requires-Dist: scipy
Requires-Dist: cyvcf2
